ccjob/__init__.py
ccjob/ccjob.py
ccjob/queue.py
ccjob/templates.py
ccjob/utils.py
ccjob-0.1.5.dist-info/AUTHORS.rst
ccjob-0.1.5.dist-info/LICENSE
ccjob-0.1.5.dist-info/METADATA
ccjob-0.1.5.dist-info/WHEEL
ccjob-0.1.5.dist-info/top_level.txt
ccjob-0.1.5.dist-info/RECORD
