Metadata-Version: 2.1
Name: ccjob
Version: 0.1.5
Summary: Easy automation for quantum chemistry jobs.
Home-page: https://github.com/spectre007/ccjob
Author: Alexander Zech
Author-email: alexzech777@gmail.com
License: MIT license
Keywords: ccjob
Platform: UNKNOWN
Classifier: Development Status :: 2 - Pre-Alpha
Classifier: Intended Audience :: Developers
Classifier: License :: OSI Approved :: MIT License
Classifier: Natural Language :: English
Classifier: Programming Language :: Python :: 3
Classifier: Programming Language :: Python :: 3.5
Classifier: Programming Language :: Python :: 3.6
Classifier: Programming Language :: Python :: 3.7
Classifier: Programming Language :: Python :: 3.8
Requires-Python: >=3.5
